QSymbolic-0.2.dev0.dist-info/DESCRIPTION.rst
QSymbolic-0.2.dev0.dist-info/METADATA
QSymbolic-0.2.dev0.dist-info/RECORD
QSymbolic-0.2.dev0.dist-info/WHEEL
QSymbolic-0.2.dev0.dist-info/metadata.json
QSymbolic-0.2.dev0.dist-info/top_level.txt
qsymbolic/__init__.py
qsymbolic/qsimu.py
qsymbolic/qsymb.py
